aind_qcportal_schema/__init__.py
aind_qcportal_schema/curation_data.py
aind_qcportal_schema/metric_value.py
aind_qcportal_schema-0.6.4.dist-info/licenses/LICENSE
aind_qcportal_schema-0.6.4.dist-info/METADATA
aind_qcportal_schema-0.6.4.dist-info/WHEEL
aind_qcportal_schema-0.6.4.dist-info/top_level.txt
aind_qcportal_schema-0.6.4.dist-info/RECORD
